impuestos_package/__init__.py
impuestos_package/calculadora.py
impuestos_package/interes.py
impuestos_package/mv.py
impuestos_package/sancion.py
impuestos_package/ufv.py
impuestos_package-0.1.0.dist-info/licenses/LICENSE
impuestos_package-0.1.0.dist-info/METADATA
impuestos_package-0.1.0.dist-info/WHEEL
impuestos_package-0.1.0.dist-info/top_level.txt
impuestos_package-0.1.0.dist-info/RECORD
