Metadata-Version: 2.4
Name: impuestos-package
Version: 0.1.0
Summary: Cálculo de deuda tributaria en Bolivia (MV, interés, sanción) con UFV.
Author-email: Martha Gonzales Chumacero <martututu651@gmail.com>
License: MIT
Project-URL: Homepage, https://github.com/MarthaGonzalesChumacero/impuestos_package
Project-URL: Issues, https://github.com/MarthaGonzalesChumacero/impuestos_package/issues
Requires-Python: >=3.8
License-File: LICENSE
Requires-Dist: requests>=2.31
Dynamic: license-file
